supports_color/__init__.py
supports_color-0.1.2.dist-info/WHEEL
supports_color-0.1.2.dist-info/METADATA
supports_color-0.1.2.dist-info/RECORD
